dependencies/__init__.py
dependencies/dependencies.py
dependencies/integrate.py
dependencies/map.py
dependencies/zss/__init__.py
dependencies/zss/compare.py
dependencies/zss/simple_tree.py
q_a_dependencies-1.0.1.dist-info/DESCRIPTION.rst
q_a_dependencies-1.0.1.dist-info/METADATA
q_a_dependencies-1.0.1.dist-info/RECORD
q_a_dependencies-1.0.1.dist-info/WHEEL
q_a_dependencies-1.0.1.dist-info/entry_points.txt
q_a_dependencies-1.0.1.dist-info/metadata.json
q_a_dependencies-1.0.1.dist-info/top_level.txt
