Metadata-Version: 2.0
Name: q-a-dependencies
Version: 1.0.1
Summary: A python project to select the most suitable answer for a question out of given answers
Home-page: https://github.com/DulanjanaYasara/dependencies
Author: Dulanjana Liyanagama
Author-email: dulanjana@wso2.com
License: MIT
Keywords: nlp dependency parse
Platform: UNKNOWN
Classifier: Development Status :: 5 - Production/Stable
Classifier: Intended Audience :: Developers
Classifier: Topic :: Software Development
Classifier: License :: OSI Approved :: MIT License
Classifier: Programming Language :: Python :: 2.7
Classifier: Programming Language :: Python :: 3.4
Classifier: Programming Language :: Python :: 3.5
Classifier: Programming Language :: Python :: 3.6
Requires-Dist: nltk
Requires-Dist: unidecode
